meta_sphinx/__init__.py
meta_sphinx/configuration.py
meta_sphinx/download_pkgs.py
meta_sphinx/generate_content.py
meta_sphinx/generate_gallery.py
meta_sphinx/generate_hosting.py
meta_sphinx/generate_pages.py
meta_sphinx/get_metadata.py
meta_sphinx/jinja.py
meta_sphinx/rst_generators.py
meta_sphinx/styles.py
meta_sphinx/_static/bs4-no-fonts.css
meta_sphinx/_static/cards.jinja
meta_sphinx/_static/categories.jinja
meta_sphinx/_static/embedded.css
meta_sphinx/_static/index-page.jinja
meta_sphinx/_static/kubernetes_volume_mounts.jinja
meta_sphinx/_static/kubernetes_volumes.jinja
meta_sphinx/_static/language-pills.css
meta_sphinx/_static/page.jinja
meta_sphinx/colors/__init__.py
meta_sphinx/colors/colors.json
meta_sphinx/colors/language-pills.css
meta_sphinx-0.1.8.dist-info/entry_points.txt
meta_sphinx-0.1.8.dist-info/WHEEL
meta_sphinx-0.1.8.dist-info/METADATA
meta_sphinx-0.1.8.dist-info/RECORD
