Metadata-Version: 2.1
Name: meta_sphinx
Version: 0.1.8
Summary: Generate an index of documentation pages from multiple sets of docs pages.
Home-page: https://github.com/elementai/meta-sphinx
License: UNKNOWN
Author: Jan Freyberg
Author-email: jan.freyberg@elementai.com
Requires-Dist: sphinx>=2.1
Requires-Dist: m2r>=0.2.1
Requires-Dist: pyyaml>=5.1
Requires-Dist: jinja2>=2.10
Requires-Dist: markdown>=3.1
Requires-Dist: python-slugify>=3.0
Requires-Dist: click>=7.0
Requires-Dist: ipython ; extra == "dev"
Requires-Dist: ipdb ; extra == "dev"
Requires-Dist: rope ; extra == "dev"
Requires-Dist: black ; extra == "dev"
Provides-Extra: dev
